README.md
setup.cfg
setup.py
sqlformat/__init__.py
sqlformat.egg-info/PKG-INFO
sqlformat.egg-info/SOURCES.txt
sqlformat.egg-info/dependency_links.txt
sqlformat.egg-info/requires.txt
sqlformat.egg-info/top_level.txt
sqlformat/models/SQLBatch.py
sqlformat/models/SQLStatement.py
sqlformat/models/__init__.py
sqlformat/persistence/ResultPersistenceStrategy.py
sqlformat/persistence/__init__.py
sqlformat/storage/AWSStorageStrategy.py
sqlformat/storage/InMemoryProcedureStorageStrategy.py
sqlformat/storage/LocalStorageStrategy.py
sqlformat/storage/StorageStrategyTemplate.py
sqlformat/storage/__init__.py