Metadata-Version: 1.1
Name: sqlformat
Version: 0.1.1
Summary: Tools for make SQL statement can accept argument and group together on run times
Home-page: https://github.com/davidNHK/sql-format
Author: David Ng
Author-email: david.ng.dev@gmail.com
License: BSD
Download-URL: https://github.com/davidNHK/sql-format/archive/0.1.1.zip
Keywords: sql,formatting,reporting
Platform: UNKNOWN
